[
  {
    "data-product-title": "Profile Design Legacy II Aerobar",
    "data-product-id": "11674542",
    "data-product-category": "",
    "data-product-is-master-product-id": "false",
    "data-product-master-product-id": "11674542",
    "data-product-brand": "Profile Design",
    "data-product-price": "A$79.49",
    "data-product-position": "1",
    "name": "Profile Design Legacy II Aerobar",
    "url": "https://www.probikekit.com.au/handlebar-spares-acc/profile-design-legacy-ii-aerobar/11674542.html",
    "images": [
      {
        "description": "Profile Design Legacy II Aerobar",
        "src": "https://s2.thcdn.com/productimg/300/300/11674542-1144550456057922.jpg"
      }
    ],
    "prices": {
      "RRP": "A$116.49",
      "rrp": "A$79.49",
      "Save:": "A$37.00"
    }
  },
  {
    "data-product-title": "Profile Design F-35 Pad Kit - 16mm",
    "data-product-id": "11674584",
    "data-product-category": "",
    "data-product-is-master-product-id": "false",
    "data-product-master-product-id": "11674584",
    "data-product-brand": "Profile Design",
    "data-product-price": "A$32.99",
    "data-product-position": "2",
    "name": "Profile Design F-35 Pad Kit - 16mm",
    "url": "https://www.probikekit.com.au/handlebar-spares-acc/profile-design-f-35-pad-kit-16mm/11674584.html",
    "images": [
      {
        "description": "Profile Design F-35 Pad Kit - 16mm",
        "src": "https://s1.thcdn.com/productimg/300/300/11674584-1254550457270318.jpg"
      }
    ],
    "prices": {
      "RRP": "A$38.99",
      "rrp": "A$32.99",
      "Save:": "A$6.00"
    }
  },
  {
    "data-product-title": "3T Revo Team Aerobar - 40cm",
    "data-product-id": "11529218",
    "data-product-category": "",
    "data-product-is-master-product-id": "false",
    "data-product-master-product-id": "11529218",
    "data-product-brand": "3T",
    "data-product-price": "A$642.99",
    "data-product-position": "3",
    "name": "3T Revo Team Aerobar - 40cm",
    "url": "https://www.probikekit.com.au/bicycle-handlebars-stems/3t-revo-team-aerobar-40cm/11529218.html",
    "images": [
      {
        "description": "3T Revo Team Aerobar - 40cm",
        "src": "https://s1.thcdn.com/productimg/300/300/11529218-9774508896986891.jpg"
      }
    ],
    "prices": {
      "RRP": "A$1164.49",
      "rrp": "A$642.99",
      "Save:": "A$521.50"
    }
  },
  {
    "data-product-title": "Deda Metal Blast Extensions TT Bars",
    "data-product-id": "11448979",
    "data-product-category": "",
    "data-product-is-master-product-id": "true",
    "data-product-master-product-id": "11448979",
    "data-product-brand": "Deda",
    "data-product-price": "A$143.49",
    "data-product-position": "4",
    "name": "Deda Metal Blast Extensions TT Bars",
    "url": "https://www.probikekit.com.au/bicycle-handlebars-stems/deda-metal-blast-extensions-tt-bars/11448979.html",
    "images": [
      {
        "description": "Deda Metal Blast Extensions TT Bars",
        "src": "https://s3.thcdn.com/productimg/300/300/11448979-1844485042852225.jpg"
      }
    ],
    "prices": {
      "from": "A$143.49",
      "Save up to:": "A$87.50"
    }
  },
  {
    "data-product-title": "Profile Design FC Bite Valve",
    "data-product-id": "11674662",
    "data-product-category": "",
    "data-product-is-master-product-id": "false",
    "data-product-master-product-id": "11674662",
    "data-product-brand": "Profile Design",
    "data-product-price": "A$11.99",
    "data-product-position": "5",
    "name": "Profile Design FC Bite Valve",
    "url": "https://www.probikekit.com.au/profile-design-fc-bite-valve/11674662.html",
    "images": [
      {
        "description": "Profile Design FC Bite Valve",
        "src": "https://s1.thcdn.com/productimg/300/300/11674662-1004550459508657.jpg"
      }
    ],
    "prices": {
      "RRP": "A$13.99",
      "rrp": "A$11.99",
      "Save:": "A$2.00"
    }
  },
  {
    "data-product-title": "Profile Design Aeria Aluminium Aerobar System - T4 42 cm",
    "data-product-id": "11674514",
    "data-product-category": "",
    "data-product-is-master-product-id": "false",
    "data-product-master-product-id": "11674514",
    "data-product-brand": "Profile Design",
    "data-product-price": "A$527.99",
    "data-product-position": "6",
    "name": "Profile Design Aeria Aluminium Aerobar System - T4 42 cm",
    "url": "https://www.probikekit.com.au/handlebar-spares-acc/profile-design-aeria-aluminium-aerobar-system-t4-42-cm/11674514.html",
    "images": [
      {
        "description": "Profile Design Aeria Aluminium Aerobar System - T4 42 cm",
        "src": "https://s4.thcdn.com/productimg/300/300/11674514-1384550454690564.jpg"
      }
    ],
    "prices": {
      "RRP": "A$678.99",
      "rrp": "A$527.99",
      "Save:": "A$151.00"
    }
  },
  {
    "data-product-title": "Profile Design Universal Aerobar Armrest Riser Kit",
    "data-product-id": "11674548",
    "data-product-category": "",
    "data-product-is-master-product-id": "false",
    "data-product-master-product-id": "11674548",
    "data-product-brand": "Profile Design",
    "data-product-price": "A$16.49",
    "data-product-position": "7",
    "name": "Profile Design Universal Aerobar Armrest Riser Kit",
    "url": "https://www.probikekit.com.au/handlebar-spares-acc/profile-design-universal-aerobar-armrest-riser-kit/11674548.html",
    "images": [
      {
        "description": "Profile Design Universal Aerobar Armrest Riser Kit",
        "src": "https://s3.thcdn.com/productimg/300/300/11674548-1744550456168700.jpg"
      }
    ],
    "prices": {
      "RRP": "A$19.49",
      "rrp": "A$16.49",
      "Save:": "A$3.00"
    }
  },
  {
    "data-product-title": "XLab Torpedo Vestito",
    "data-product-id": "11075907",
    "data-product-category": "",
    "data-product-is-master-product-id": "false",
    "data-product-master-product-id": "11075907",
    "data-product-brand": "Xlab",
    "data-product-price": "A$34.99",
    "data-product-position": "8",
    "name": "XLab Torpedo Vestito",
    "url": "https://www.probikekit.com.au/cycling-accessories-nc/xlab-torpedo-vestito/11075907.html",
    "images": [
      {
        "description": "XLab Torpedo Vestito",
        "src": "https://s3.thcdn.com/productimg/300/300/11075907-1454550149211184.jpg"
      }
    ],
    "prices": {
      "RRP": "A$44.99",
      "rrp": "A$34.99",
      "Save:": "A$10.00"
    }
  },
  {
    "data-product-title": "Profile Design Riser Kit",
    "data-product-id": "11674374",
    "data-product-category": "",
    "data-product-is-master-product-id": "true",
    "data-product-master-product-id": "11674374",
    "data-product-brand": "Profile Design",
    "data-product-price": "A$41.49",
    "data-product-position": "9",
    "name": "Profile Design Riser Kit",
    "url": "https://www.probikekit.com.au/handlebar-spares-acc/profile-design-riser-kit/11674374.html",
    "images": [
      {
        "description": "Profile Design Riser Kit",
        "src": "https://s2.thcdn.com/productimg/300/300/11674374-8554550452425036.jpg"
      }
    ],
    "prices": {
      "from": "A$41.49",
      "Save up to:": "A$17.00"
    }
  },
  {
    "data-product-title": "Deda Carbon Blast Clip On Tri Handlebars",
    "data-product-id": "10916768",
    "data-product-category": "",
    "data-product-is-master-product-id": "true",
    "data-product-master-product-id": "10916768",
    "data-product-brand": "Deda",
    "data-product-price": "A$277.99",
    "data-product-position": "10",
    "name": "Deda Carbon Blast Clip On Tri Handlebars",
    "url": "https://www.probikekit.com.au/bicycle-handlebars-stems/deda-carbon-blast-clip-on-tri-handlebars/10916768.html",
    "images": [
      {
        "description": "Deda Carbon Blast Clip On Tri Handlebars",
        "src": "https://s1.thcdn.com/productimg/0/300/300/68/10916768-1394556545-481732.jpg"
      }
    ],
    "prices": {
      "RRP": "A$492.99",
      "rrp": "A$277.99",
      "Save:": "A$215.00"
    }
  },
  {
    "data-product-title": "Profile Design F-19 Velcro Back Pad Set",
    "data-product-id": "11674588",
    "data-product-category": "",
    "data-product-is-master-product-id": "false",
    "data-product-master-product-id": "11674588",
    "data-product-brand": "Profile Design",
    "data-product-price": "A$32.49",
    "data-product-position": "11",
    "name": "Profile Design F-19 Velcro Back Pad Set",
    "url": "https://www.probikekit.com.au/handlebar-spares-acc/profile-design-f-19-velcro-back-pad-set/11674588.html",
    "images": [
      {
        "description": "Profile Design F-19 Velcro Back Pad Set",
        "src": "https://s2.thcdn.com/productimg/300/300/11674588-1304550457464916.jpg"
      }
    ],
    "prices": {
      "RRP": "A$38.99",
      "rrp": "A$32.49",
      "Save:": "A$6.50"
    }
  },
  {
    "data-product-title": "Profile Design F-40 Pad Kit - 16mm",
    "data-product-id": "11674569",
    "data-product-category": "",
    "data-product-is-master-product-id": "false",
    "data-product-master-product-id": "11674569",
    "data-product-brand": "Profile Design",
    "data-product-price": "A$39.99",
    "data-product-position": "12",
    "name": "Profile Design F-40 Pad Kit - 16mm",
    "url": "https://www.probikekit.com.au/handlebar-spares-acc/profile-design-f-40-pad-kit-16mm/11674569.html",
    "images": [
      {
        "description": "Profile Design F-40 Pad Kit - 16mm",
        "src": "https://s1.thcdn.com/productimg/300/300/11674569-7774550879638785.jpg"
      }
    ],
    "prices": {
      "RRP": "A$48.49",
      "rrp": "A$39.99",
      "Save:": "A$8.50"
    }
  },
  {
    "data-product-title": "Deda Expander Bung",
    "data-product-id": "10916969",
    "data-product-category": "",
    "data-product-is-master-product-id": "true",
    "data-product-master-product-id": "10916969",
    "data-product-brand": "Deda",
    "data-product-price": "A$20.99",
    "data-product-position": "13",
    "name": "Deda Expander Bung",
    "url": "https://www.probikekit.com.au/handlebar-spares-acc/deda-expander-bung/10916969.html",
    "images": [
      {
        "description": "Deda Expander Bung",
        "src": "https://s2.thcdn.com/productimg/300/300/10916969-1914609990970265.jpg"
      }
    ],
    "prices": {
      "RRP": "A$29.49",
      "rrp": "A$20.99",
      "Save:": "A$8.50"
    }
  },
  {
    "data-product-title": "Profile Design Aero HC Bracket with Integrated Computer Mount",
    "data-product-id": "11674657",
    "data-product-category": "",
    "data-product-is-master-product-id": "false",
    "data-product-master-product-id": "11674657",
    "data-product-brand": "Profile Design",
    "data-product-price": "A$38.99",
    "data-product-position": "14",
    "name": "Profile Design Aero HC Bracket with Integrated Computer Mount",
    "url": "https://www.probikekit.com.au/cycling-accessories/profile-design-aero-hc-bracket-with-integrated-computer-mount/11674657.html",
    "images": [
      {
        "description": "Profile Design Aero HC Bracket with Integrated Computer Mount",
        "src": "https://s1.thcdn.com/productimg/300/300/11674657-1664550459443734.jpg"
      }
    ],
    "prices": {
      "RRP": "A$48.49",
      "rrp": "A$38.99",
      "Save:": "A$9.50"
    }
  },
  {
    "data-product-title": "Profile Design Tank Storage Case",
    "data-product-id": "11674676",
    "data-product-category": "",
    "data-product-is-master-product-id": "false",
    "data-product-master-product-id": "11674676",
    "data-product-brand": "Profile Design",
    "data-product-price": "A$57.99",
    "data-product-position": "15",
    "name": "Profile Design Tank Storage Case",
    "url": "https://www.probikekit.com.au/profile-design-tank-storage-case/11674676.html",
    "images": [
      {
        "description": "Profile Design Tank Storage Case",
        "src": "https://s1.thcdn.com/productimg/300/300/11674676-1724550459967021.jpg"
      }
    ],
    "prices": {
      "RRP": "A$77.99",
      "rrp": "A$57.99",
      "Save:": "A$20.00"
    }
  },
  {
    "data-product-title": "Profile Design J5 Type Armrest Bracket Kit",
    "data-product-id": "11674549",
    "data-product-category": "",
    "data-product-is-master-product-id": "false",
    "data-product-master-product-id": "11674549",
    "data-product-brand": "Profile Design",
    "data-product-price": "A$120.49",
    "data-product-position": "16",
    "name": "Profile Design J5 Type Armrest Bracket Kit",
    "url": "https://www.probikekit.com.au/handlebar-spares-acc/profile-design-j5-type-armrest-bracket-kit/11674549.html",
    "images": [
      {
        "description": "Profile Design J5 Type Armrest Bracket Kit",
        "src": "https://s1.thcdn.com/productimg/300/300/11674549-3814550456201859.jpg"
      }
    ],
    "prices": {
      "RRP": "A$174.99",
      "rrp": "A$120.49",
      "Save:": "A$54.50"
    }
  },
  {
    "data-product-title": "Profile Design F-40 AL Armrest Kit",
    "data-product-id": "11674562",
    "data-product-category": "",
    "data-product-is-master-product-id": "false",
    "data-product-master-product-id": "11674562",
    "data-product-brand": "Profile Design",
    "data-product-price": "A$85.99",
    "data-product-position": "17",
    "name": "Profile Design F-40 AL Armrest Kit",
    "url": "https://www.probikekit.com.au/handlebar-spares-acc/profile-design-f-40-al-armrest-kit/11674562.html",
    "images": [
      {
        "description": "Profile Design F-40 AL Armrest Kit",
        "src": "https://s4.thcdn.com/productimg/300/300/11674562-1124550456524923.jpg"
      }
    ],
    "prices": {
      "RRP": "A$116.49",
      "rrp": "A$85.99",
      "Save:": "A$30.50"
    }
  },
  {
    "data-product-title": "Profile Design F-40 TT RACE Pad Kit 10mm",
    "data-product-id": "11674573",
    "data-product-category": "",
    "data-product-is-master-product-id": "false",
    "data-product-master-product-id": "11674573",
    "data-product-brand": "Profile Design",
    "data-product-price": "A$38.99",
    "data-product-position": "18",
    "name": "Profile Design F-40 TT RACE Pad Kit 10mm",
    "url": "https://www.probikekit.com.au/handlebar-spares-acc/profile-design-f-40-tt-race-pad-kit-10mm/11674573.html",
    "images": [
      {
        "description": "Profile Design F-40 TT RACE Pad Kit 10mm",
        "src": "https://s2.thcdn.com/productimg/300/300/11674573-1744550879765703.jpg"
      }
    ],
    "prices": {
      "RRP": "A$48.49",
      "rrp": "A$38.99",
      "Save:": "A$9.50"
    }
  },
  {
    "data-product-title": "Deda Parabolica Due Clip-On Bars - Black - 31.7mm",
    "data-product-id": "11855712",
    "data-product-category": "",
    "data-product-is-master-product-id": "false",
    "data-product-master-product-id": "11855712",
    "data-product-brand": "Deda",
    "data-product-price": "A$181.49",
    "data-product-position": "19",
    "name": "Deda Parabolica Due Clip-On Bars - Black - 31.7mm",
    "url": "https://www.probikekit.com.au/bicycle-handlebars-stems/deda-parabolica-due-clip-on-bars-black-31.7mm/11855712.html",
    "images": [
      {
        "description": "Deda Parabolica Due Clip-On Bars - Black - 31.7mm",
        "src": "https://s4.thcdn.com/productimg/300/300/11855712-7134606422556449.jpg"
      }
    ],
    "prices": {
      "RRP": "A$213.49",
      "rrp": "A$181.49",
      "Save:": "A$32.00"
    }
  },
  {
    "data-product-title": "3T Carbon Handlebar Extensions - Straight",
    "data-product-id": "10770228",
    "data-product-category": "",
    "data-product-is-master-product-id": "true",
    "data-product-master-product-id": "10770228",
    "data-product-brand": "3T",
    "data-product-price": "A$80.99",
    "data-product-position": "20",
    "name": "3T Carbon Handlebar Extensions - Straight",
    "url": "https://www.probikekit.com.au/bicycle-handlebars-stems/3t-carbon-handlebar-extensions-straight/10770228.html",
    "images": [
      {
        "description": "3T Carbon Handlebar Extensions - Straight",
        "src": "https://s3.thcdn.com/productimg/300/300/10770228-4264528143584433.jpg"
      }
    ],
    "prices": {
      "RRP": "A$194.49",
      "rrp": "A$80.99",
      "Save:": "A$113.50"
    }
  },
  {
    "data-product-title": "Deda Espresso Carbon TT Bar - Black",
    "data-product-id": "11855715",
    "data-product-category": "",
    "data-product-is-master-product-id": "false",
    "data-product-master-product-id": "11855715",
    "data-product-brand": "Deda",
    "data-product-price": "A$1327.49",
    "data-product-position": "21",
    "name": "Deda Espresso Carbon TT Bar - Black",
    "url": "https://www.probikekit.com.au/bicycle-handlebars-stems/deda-espresso-carbon-tt-bar-black/11855715.html",
    "images": [
      {
        "description": "Deda Espresso Carbon TT Bar - Black",
        "src": "https://s3.thcdn.com/productimg/300/300/11855715-1504606422678333.jpg"
      }
    ],
    "prices": {
      "RRP": "A$1561.99",
      "rrp": "A$1327.49",
      "Save:": "A$234.50"
    }
  },
  {
    "data-product-title": "Profile Design Universal Aerobar Bracket Riser Kit",
    "data-product-id": "11674545",
    "data-product-category": "",
    "data-product-is-master-product-id": "false",
    "data-product-master-product-id": "11674545",
    "data-product-brand": "Profile Design",
    "data-product-price": "A$46.49",
    "data-product-position": "22",
    "name": "Profile Design Universal Aerobar Bracket Riser Kit",
    "url": "https://www.probikekit.com.au/handlebar-spares-acc/profile-design-universal-aerobar-bracket-riser-kit/11674545.html",
    "images": [
      {
        "description": "Profile Design Universal Aerobar Bracket Riser Kit",
        "src": "https://s2.thcdn.com/productimg/300/300/11674545-4254550456128659.jpg"
      }
    ],
    "prices": {
      "RRP": "A$58.49",
      "rrp": "A$46.49",
      "Save:": "A$12.00"
    }
  },
  {
    "data-product-title": "Profile Design F-40 RACE Pad Kit - 10mm",
    "data-product-id": "11674571",
    "data-product-category": "",
    "data-product-is-master-product-id": "false",
    "data-product-master-product-id": "11674571",
    "data-product-brand": "Profile Design",
    "data-product-price": "A$38.99",
    "data-product-position": "23",
    "name": "Profile Design F-40 RACE Pad Kit - 10mm",
    "url": "https://www.probikekit.com.au/handlebar-spares-acc/profile-design-f-40-race-pad-kit-10mm/11674571.html",
    "images": [
      {
        "description": "Profile Design F-40 RACE Pad Kit - 10mm",
        "src": "https://s4.thcdn.com/productimg/300/300/11674571-1904550456832699.jpg"
      }
    ],
    "prices": {
      "RRP": "A$48.49",
      "rrp": "A$38.99",
      "Save:": "A$9.50"
    }
  },
  {
    "data-product-title": "Deda Kronos Tri Due Handlebars",
    "data-product-id": "10916756",
    "data-product-category": "",
    "data-product-is-master-product-id": "true",
    "data-product-master-product-id": "10916756",
    "data-product-brand": "Deda",
    "data-product-price": "A$709.49",
    "data-product-position": "24",
    "name": "Deda Kronos Tri Due Handlebars",
    "url": "https://www.probikekit.com.au/bicycle-handlebars-stems/deda-kronos-tri-due-handlebars/10916756.html",
    "images": [
      {
        "description": "Deda Kronos Tri Due Handlebars",
        "src": "https://s2.thcdn.com/productimg/0/300/300/56/10916756-1394556545-481478.jpg"
      }
    ],
    "prices": {
      "RRP": "A$1144.99",
      "rrp": "A$709.49",
      "Save:": "A$435.50"
    }
  },
  {
    "data-product-title": "Profile Design T2+ Carbon Aerobar Extensions",
    "data-product-id": "11674610",
    "data-product-category": "",
    "data-product-is-master-product-id": "false",
    "data-product-master-product-id": "11674610",
    "data-product-brand": "Profile Design",
    "data-product-price": "A$153.49",
    "data-product-position": "25",
    "name": "Profile Design T2+ Carbon Aerobar Extensions",
    "url": "https://www.probikekit.com.au/handlebar-spares-acc/profile-design-t2-carbon-aerobar-extensions/11674610.html",
    "images": [
      {
        "description": "Profile Design T2+ Carbon Aerobar Extensions",
        "src": "https://s4.thcdn.com/productimg/300/300/11674610-1254550457846213.jpg"
      }
    ],
    "prices": {
      "RRP": "A$213.49",
      "rrp": "A$153.49",
      "Save:": "A$60.00"
    }
  },
  {
    "data-product-title": "Profile Design WING/10a Base Bar",
    "data-product-id": "11674401",
    "data-product-category": "",
    "data-product-is-master-product-id": "true",
    "data-product-master-product-id": "11674401",
    "data-product-brand": "Profile Design",
    "data-product-price": "A$98.99",
    "data-product-position": "26",
    "name": "Profile Design WING/10a Base Bar",
    "url": "https://www.probikekit.com.au/bicycle-handlebars-stems/profile-design-wing/10a-base-bar/11674401.html",
    "images": [
      {
        "description": "Profile Design WING/10a Base Bar",
        "src": "https://s4.thcdn.com/productimg/300/300/11674401-6884550452693764.jpg"
      }
    ],
    "prices": {
      "from": "A$98.99",
      "Save up to:": "A$37.00"
    }
  },
  {
    "data-product-title": "Profile Design T5+ Carbon Aerobar",
    "data-product-id": "11674526",
    "data-product-category": "",
    "data-product-is-master-product-id": "false",
    "data-product-master-product-id": "11674526",
    "data-product-brand": "Profile Design",
    "data-product-price": "A$272.49",
    "data-product-position": "27",
    "name": "Profile Design T5+ Carbon Aerobar",
    "url": "https://www.probikekit.com.au/handlebar-spares-acc/profile-design-t5-carbon-aerobar/11674526.html",
    "images": [
      {
        "description": "Profile Design T5+ Carbon Aerobar",
        "src": "https://s4.thcdn.com/productimg/300/300/11674526-1984550455290672.jpg"
      }
    ],
    "prices": {
      "RRP": "A$387.99",
      "rrp": "A$272.49",
      "Save:": "A$115.50"
    }
  },
  {
    "data-product-title": "Profile Design T5+ Carbon Aerobar Extensions",
    "data-product-id": "11674619",
    "data-product-category": "",
    "data-product-is-master-product-id": "false",
    "data-product-master-product-id": "11674619",
    "data-product-brand": "Profile Design",
    "data-product-price": "A$155.49",
    "data-product-position": "28",
    "name": "Profile Design T5+ Carbon Aerobar Extensions",
    "url": "https://www.probikekit.com.au/handlebar-spares-acc/profile-design-t5-carbon-aerobar-extensions/11674619.html",
    "images": [
      {
        "description": "Profile Design T5+ Carbon Aerobar Extensions",
        "src": "https://s4.thcdn.com/productimg/300/300/11674619-6984550458080201.jpg"
      }
    ],
    "prices": {
      "RRP": "A$213.49",
      "rrp": "A$155.49",
      "Save:": "A$58.00"
    }
  },
  {
    "data-product-title": "Deda Parabolica Zero Clip-On Bars - Black - 31.7mm",
    "data-product-id": "11855714",
    "data-product-category": "",
    "data-product-is-master-product-id": "false",
    "data-product-master-product-id": "11855714",
    "data-product-brand": "Deda",
    "data-product-price": "A$181.49",
    "data-product-position": "29",
    "name": "Deda Parabolica Zero Clip-On Bars - Black - 31.7mm",
    "url": "https://www.probikekit.com.au/bicycle-handlebars-stems/deda-parabolica-zero-clip-on-bars-black-31.7mm/11855714.html",
    "images": [
      {
        "description": "Deda Parabolica Zero Clip-On Bars - Black - 31.7mm",
        "src": "https://s4.thcdn.com/productimg/300/300/11855714-2134606422637596.jpg"
      }
    ],
    "prices": {
      "RRP": "A$213.49",
      "rrp": "A$181.49",
      "Save:": "A$32.00"
    }
  },
  {
    "data-product-title": "Profile Design Foam Disk Pad Set for Century/Legacy/Legacy 2",
    "data-product-id": "11674594",
    "data-product-category": "",
    "data-product-is-master-product-id": "false",
    "data-product-master-product-id": "11674594",
    "data-product-brand": "Profile Design",
    "data-product-price": "A$12.99",
    "data-product-position": "30",
    "name": "Profile Design Foam Disk Pad Set for Century/Legacy/Legacy 2",
    "url": "https://www.probikekit.com.au/handlebar-spares-acc/profile-design-foam-disk-pad-set-for-century/legacy/legacy-2/11674594.html",
    "images": [
      {
        "description": "Profile Design Foam Disk Pad Set for Century/Legacy/Legacy 2",
        "src": "https://s1.thcdn.com/productimg/300/300/11674594-7244550457560442.jpg"
      }
    ],
    "prices": {
      "RRP": "A$15.99",
      "rrp": "A$12.99",
      "Save:": "A$3.00"
    }
  },
  {
    "data-product-title": "Deda Bridge for Carbon/Metal Blast",
    "data-product-id": "11855726",
    "data-product-category": "",
    "data-product-is-master-product-id": "false",
    "data-product-master-product-id": "11855726",
    "data-product-brand": "Deda",
    "data-product-price": "A$29.99",
    "data-product-position": "1",
    "name": "Deda Bridge for Carbon/Metal Blast",
    "url": "https://www.probikekit.com.au/bicycle-handlebars-stems/deda-bridge-for-carbon-metal-blast/11855726.html",
    "images": [
      {
        "description": "Deda Bridge for Carbon/Metal Blast",
        "src": "https://s2.thcdn.com/productimg/300/300/11855726-1004606423589193.jpg"
      }
    ],
    "prices": {
      "RRP": "A$34.99",
      "rrp": "A$29.99",
      "Save:": "A$5.00"
    }
  },
  {
    "data-product-title": "Profile Design Aerodrink Parts Kit",
    "data-product-id": "11674664",
    "data-product-category": "",
    "data-product-is-master-product-id": "false",
    "data-product-master-product-id": "11674664",
    "data-product-brand": "Profile Design",
    "data-product-price": "A$14.49",
    "data-product-position": "2",
    "name": "Profile Design Aerodrink Parts Kit",
    "url": "https://www.probikekit.com.au/profile-design-aerodrink-parts-kit/11674664.html",
    "images": [
      {
        "description": "Profile Design Aerodrink Parts Kit",
        "src": "https://s4.thcdn.com/productimg/300/300/11674664-3564550459629464.jpg"
      }
    ],
    "prices": {
      "RRP": "A$17.49",
      "rrp": "A$14.49",
      "Save:": "A$3.00"
    }
  },
  {
    "data-product-title": "Profile Design Svet TT Carbon Base Bar",
    "data-product-id": "11674397",
    "data-product-category": "",
    "data-product-is-master-product-id": "true",
    "data-product-master-product-id": "11674397",
    "data-product-brand": "Profile Design",
    "data-product-price": "A$261.49",
    "data-product-position": "3",
    "name": "Profile Design Svet TT Carbon Base Bar",
    "url": "https://www.probikekit.com.au/bicycle-handlebars-stems/profile-design-svet-tt-carbon-base-bar/11674397.html",
    "images": [
      {
        "description": "Profile Design Svet TT Carbon Base Bar",
        "src": "https://s2.thcdn.com/productimg/300/300/11674397-9754550452594596.jpg"
      }
    ],
    "prices": {
      "from": "A$261.49",
      "Save up to:": "A$126.50"
    }
  },
  {
    "data-product-title": "Deda Parabolica Uno Clip-On Bars - Black - 31.7mm",
    "data-product-id": "11855713",
    "data-product-category": "",
    "data-product-is-master-product-id": "false",
    "data-product-master-product-id": "11855713",
    "data-product-brand": "Deda",
    "data-product-price": "A$181.49",
    "data-product-position": "4",
    "name": "Deda Parabolica Uno Clip-On Bars - Black - 31.7mm",
    "url": "https://www.probikekit.com.au/bicycle-handlebars-stems/deda-parabolica-uno-clip-on-bars-black-31.7mm/11855713.html",
    "images": [
      {
        "description": "Deda Parabolica Uno Clip-On Bars - Black - 31.7mm",
        "src": "https://s4.thcdn.com/productimg/300/300/11855713-1004606422589833.jpg"
      }
    ],
    "prices": {
      "RRP": "A$213.49",
      "rrp": "A$181.49",
      "Save:": "A$32.00"
    }
  },
  {
    "data-product-title": "Deda Brooklyn Bridge",
    "data-product-id": "10916766",
    "data-product-category": "",
    "data-product-is-master-product-id": "true",
    "data-product-master-product-id": "10916766",
    "data-product-brand": "Deda",
    "data-product-price": "A$32.99",
    "data-product-position": "5",
    "name": "Deda Brooklyn Bridge",
    "url": "https://www.probikekit.com.au/handlebar-spares-acc/deda-brooklyn-bridge/10916766.html",
    "images": [
      {
        "description": "Deda Brooklyn Bridge",
        "src": "https://s4.thcdn.com/productimg/0/300/300/66/10916766-1394556545-481991.jpg"
      }
    ],
    "prices": {
      "RRP": "A$42.99",
      "rrp": "A$32.99",
      "Save:": "A$10.00"
    }
  },
  {
    "data-product-title": "XLab Torpedo Versa Alloy Mount",
    "data-product-id": "11629865",
    "data-product-category": "",
    "data-product-is-master-product-id": "false",
    "data-product-master-product-id": "11629865",
    "data-product-brand": "Xlab",
    "data-product-price": "A$46.99",
    "data-product-position": "6",
    "name": "XLab Torpedo Versa Alloy Mount",
    "url": "https://www.probikekit.com.au/cycling-accessories/xlab-torpedo-versa-alloy-mount/11629865.html",
    "images": [
      {
        "description": "XLab Torpedo Versa Alloy Mount",
        "src": "https://s4.thcdn.com/productimg/300/300/11629865-1994550151363390.jpg"
      }
    ],
    "prices": {
      "RRP": "A$64.49",
      "rrp": "A$46.99",
      "Save:": "A$17.50"
    }
  },
  {
    "data-product-title": "Deda Kronos Tri Handlebars",
    "data-product-id": "10916754",
    "data-product-category": "",
    "data-product-is-master-product-id": "true",
    "data-product-master-product-id": "10916754",
    "data-product-brand": "Deda",
    "data-product-price": "A$659.99",
    "data-product-position": "7",
    "name": "Deda Kronos Tri Handlebars",
    "url": "https://www.probikekit.com.au/bicycle-handlebars-stems/deda-kronos-tri-handlebars/10916754.html",
    "images": [
      {
        "description": "Deda Kronos Tri Handlebars",
        "src": "https://s1.thcdn.com/productimg/0/300/300/54/10916754-1394556545-481570.jpg"
      }
    ],
    "prices": {
      "RRP": "A$1144.99",
      "rrp": "A$659.99",
      "Save:": "A$485.00"
    }
  },
  {
    "data-product-title": "Profile Design Stoker Base Bar 26 47cm - Black",
    "data-product-id": "11674620",
    "data-product-category": "",
    "data-product-is-master-product-id": "false",
    "data-product-master-product-id": "11674620",
    "data-product-brand": "Profile Design",
    "data-product-price": "A$51.49",
    "data-product-position": "8",
    "name": "Profile Design Stoker Base Bar 26 47cm - Black",
    "url": "https://www.probikekit.com.au/handlebar-spares-acc/profile-design-stoker-base-bar-26-47cm-black/11674620.html",
    "images": [
      {
        "description": "Profile Design Stoker Base Bar 26 47cm - Black",
        "src": "https://s3.thcdn.com/productimg/300/300/11674620-2834550458231176.jpg"
      }
    ],
    "prices": {
      "RRP": "A$67.99",
      "rrp": "A$51.49",
      "Save:": "A$16.50"
    }
  },
  {
    "data-product-title": "Profile Design F-35 TT Micro AL Armrest Kit",
    "data-product-id": "11674574",
    "data-product-category": "",
    "data-product-is-master-product-id": "false",
    "data-product-master-product-id": "11674574",
    "data-product-brand": "Profile Design",
    "data-product-price": "A$56.49",
    "data-product-position": "9",
    "name": "Profile Design F-35 TT Micro AL Armrest Kit",
    "url": "https://www.probikekit.com.au/handlebar-spares-acc/profile-design-f-35-tt-micro-al-armrest-kit/11674574.html",
    "images": [
      {
        "description": "Profile Design F-35 TT Micro AL Armrest Kit",
        "src": "https://s2.thcdn.com/productimg/300/300/11674574-1084550456866902.jpg"
      }
    ],
    "prices": {
      "RRP": "A$77.99",
      "rrp": "A$56.49",
      "Save:": "A$21.50"
    }
  },
  {
    "data-product-title": "Profile Design T2+ Draft Legal Aerobar Extensions",
    "data-product-id": "11674598",
    "data-product-category": "",
    "data-product-is-master-product-id": "false",
    "data-product-master-product-id": "11674598",
    "data-product-brand": "Profile Design",
    "data-product-price": "A$72.99",
    "data-product-position": "10",
    "name": "Profile Design T2+ Draft Legal Aerobar Extensions",
    "url": "https://www.probikekit.com.au/handlebar-spares-acc/profile-design-t2-draft-legal-aerobar-extensions/11674598.html",
    "images": [
      {
        "description": "Profile Design T2+ Draft Legal Aerobar Extensions",
        "src": "https://s1.thcdn.com/productimg/300/300/11674598-1714550879818341.jpg"
      }
    ],
    "prices": {
      "RRP": "A$96.99",
      "rrp": "A$72.99",
      "Save:": "A$24.00"
    }
  },
  {
    "data-product-title": "Profile Design Aeria Ultimate Aerobar",
    "data-product-id": "11674512",
    "data-product-category": "",
    "data-product-is-master-product-id": "false",
    "data-product-master-product-id": "11674512",
    "data-product-brand": "Profile Design",
    "data-product-price": "A$1154.49",
    "data-product-position": "11",
    "name": "Profile Design Aeria Ultimate Aerobar",
    "url": "https://www.probikekit.com.au/handlebar-spares-acc/profile-design-aeria-ultimate-aerobar/11674512.html",
    "images": [
      {
        "description": "Profile Design Aeria Ultimate Aerobar",
        "src": "https://s2.thcdn.com/productimg/300/300/11674512-1744550454587916.jpg"
      }
    ],
    "prices": {
      "RRP": "A$1551.99",
      "rrp": "A$1154.49",
      "Save:": "A$397.50"
    }
  },
  {
    "data-product-title": "Profile Design T2+ AL Aerobar Extensions",
    "data-product-id": "11674597",
    "data-product-category": "",
    "data-product-is-master-product-id": "false",
    "data-product-master-product-id": "11674597",
    "data-product-brand": "Profile Design",
    "data-product-price": "A$75.99",
    "data-product-position": "12",
    "name": "Profile Design T2+ AL Aerobar Extensions",
    "url": "https://www.probikekit.com.au/handlebar-spares-acc/profile-design-t2-al-aerobar-extensions/11674597.html",
    "images": [
      {
        "description": "Profile Design T2+ AL Aerobar Extensions",
        "src": "https://s3.thcdn.com/productimg/300/300/11674597-1444550457608589.jpg"
      }
    ],
    "prices": {
      "RRP": "A$96.99",
      "rrp": "A$75.99",
      "Save:": "A$21.00"
    }
  },
  {
    "data-product-title": "Cinelli Gel Bar Cushion Kit",
    "data-product-id": "11699639",
    "data-product-category": "",
    "data-product-is-master-product-id": "false",
    "data-product-master-product-id": "11699639",
    "data-product-brand": "Cinelli",
    "data-product-price": "A$6.99",
    "data-product-position": "13",
    "name": "Cinelli Gel Bar Cushion Kit",
    "url": "https://www.probikekit.com.au/handlebar-spares-acc/cinelli-gel-bar-cushion-kit/11699639.html",
    "images": [
      {
        "description": "Cinelli Gel Bar Cushion Kit",
        "src": "https://s4.thcdn.com/productimg/300/300/11699639-3654565421977136.jpg"
      }
    ],
    "prices": {
      "RRP": "A$7.99",
      "rrp": "A$6.99",
      "Save:": "A$1.00"
    }
  },
  {
    "data-product-title": "Deda Dabar Tri Aero Handlebars",
    "data-product-id": "10916758",
    "data-product-category": "",
    "data-product-is-master-product-id": "true",
    "data-product-master-product-id": "10916758",
    "data-product-brand": "Deda",
    "data-product-price": "A$176.49",
    "data-product-position": "14",
    "name": "Deda Dabar Tri Aero Handlebars",
    "url": "https://www.probikekit.com.au/bicycle-handlebars-stems/deda-dabar-tri-aero-handlebars/10916758.html",
    "images": [
      {
        "description": "Deda Dabar Tri Aero Handlebars",
        "src": "https://s4.thcdn.com/productimg/0/300/300/58/10916758-1395742995-806823.jpg"
      }
    ],
    "prices": {
      "RRP": "A$325.99",
      "rrp": "A$176.49",
      "Save:": "A$149.50"
    }
  },
  {
    "data-product-title": "Oval Concepts A700 Clip-On Handlebar Extensions",
    "data-product-id": "10770212",
    "data-product-category": "",
    "data-product-is-master-product-id": "true",
    "data-product-master-product-id": "10770212",
    "data-product-brand": "",
    "data-product-price": "A$41.49",
    "data-product-position": "15",
    "name": "Oval Concepts A700 Clip-On Handlebar Extensions",
    "url": "https://www.probikekit.com.au/bicycle-handlebars-stems/oval-concepts-a700-clip-on-handlebar-extensions/10770212.html",
    "images": [
      {
        "description": "Oval Concepts A700 Clip-On Handlebar Extensions",
        "src": "https://s1.thcdn.com/productimg/0/300/300/12/10770212-1363093550-967534.jpg"
      }
    ],
    "prices": {
      "RRP": "A$80.99",
      "rrp": "A$41.49",
      "Save:": "A$39.50"
    }
  },
  {
    "data-product-title": "Profile Design Forged Non Flip Up Bracket Kit - 31.8mm",
    "data-product-id": "11674491",
    "data-product-category": "",
    "data-product-is-master-product-id": "false",
    "data-product-master-product-id": "11674491",
    "data-product-brand": "Profile Design",
    "data-product-price": "A$44.99",
    "data-product-position": "16",
    "name": "Profile Design Forged Non Flip Up Bracket Kit - 31.8mm",
    "url": "https://www.probikekit.com.au/handlebar-spares-acc/profile-design-forged-non-flip-up-bracket-kit-31.8mm/11674491.html",
    "images": [
      {
        "description": "Profile Design Forged Non Flip Up Bracket Kit - 31.8mm",
        "src": "https://s4.thcdn.com/productimg/300/300/11674491-1574550453698737.jpg"
      }
    ],
    "prices": {
      "RRP": "A$58.49",
      "rrp": "A$44.99",
      "Save:": "A$13.50"
    }
  },
  {
    "data-product-title": "Deda Superzero Clip-on TT Extensions - Black",
    "data-product-id": "12003680",
    "data-product-category": "",
    "data-product-is-master-product-id": "false",
    "data-product-master-product-id": "12003680",
    "data-product-brand": "Deda",
    "data-product-price": "A$285.49",
    "data-product-position": "17",
    "name": "Deda Superzero Clip-on TT Extensions - Black",
    "url": "https://www.probikekit.com.au/bicycle-handlebars-stems/deda-superzero-clip-on-tt-extensions-black/12003680.html",
    "images": [
      {
        "description": "Deda Superzero Clip-on TT Extensions - Black",
        "src": "https://s3.thcdn.com/productimg/300/300/12003680-1404639518090375.jpg"
      }
    ],
    "prices": {
      "RRP": "A$335.99",
      "rrp": "A$285.49",
      "Save:": "A$50.50"
    }
  },
  {
    "data-product-title": "Deda Tribar Carbon Aero Bar - Black",
    "data-product-id": "11855716",
    "data-product-category": "",
    "data-product-is-master-product-id": "false",
    "data-product-master-product-id": "11855716",
    "data-product-brand": "Deda",
    "data-product-price": "A$346.49",
    "data-product-position": "18",
    "name": "Deda Tribar Carbon Aero Bar - Black",
    "url": "https://www.probikekit.com.au/bicycle-handlebars-stems/deda-tribar-carbon-aero-bar-black/11855716.html",
    "images": [
      {
        "description": "Deda Tribar Carbon Aero Bar - Black",
        "src": "https://s4.thcdn.com/productimg/300/300/11855716-9634606422750000.jpg"
      }
    ],
    "prices": {
      "RRP": "A$407.49",
      "rrp": "A$346.49",
      "Save:": "A$61.00"
    }
  },
  {
    "data-product-title": "Profile Design V2+ Carbon Aerobar",
    "data-product-id": "11674515",
    "data-product-category": "",
    "data-product-is-master-product-id": "false",
    "data-product-master-product-id": "11674515",
    "data-product-brand": "Profile Design",
    "data-product-price": "A$273.49",
    "data-product-position": "19",
    "name": "Profile Design V2+ Carbon Aerobar",
    "url": "https://www.probikekit.com.au/handlebar-spares-acc/profile-design-v2-carbon-aerobar/11674515.html",
    "images": [
      {
        "description": "Profile Design V2+ Carbon Aerobar",
        "src": "https://s1.thcdn.com/productimg/300/300/11674515-2034550454848520.jpg"
      }
    ],
    "prices": {
      "RRP": "A$387.99",
      "rrp": "A$273.49",
      "Save:": "A$114.50"
    }
  },
  {
    "data-product-title": "Profile Design J5 BTA Bridge",
    "data-product-id": "11674560",
    "data-product-category": "",
    "data-product-is-master-product-id": "false",
    "data-product-master-product-id": "11674560",
    "data-product-brand": "Profile Design",
    "data-product-price": "A$46.49",
    "data-product-position": "20",
    "name": "Profile Design J5 BTA Bridge",
    "url": "https://www.probikekit.com.au/handlebar-spares-acc/profile-design-j5-bta-bridge/11674560.html",
    "images": [
      {
        "description": "Profile Design J5 BTA Bridge",
        "src": "https://s1.thcdn.com/productimg/300/300/11674560-3774550456415144.jpg"
      }
    ],
    "prices": {
      "RRP": "A$58.49",
      "rrp": "A$46.49",
      "Save:": "A$12.00"
    }
  },
  {
    "data-product-title": "Deda Crononero Team Tri Handlebars",
    "data-product-id": "10916763",
    "data-product-category": "",
    "data-product-is-master-product-id": "true",
    "data-product-master-product-id": "10916763",
    "data-product-brand": "Deda",
    "data-product-price": "A$56.49",
    "data-product-position": "21",
    "name": "Deda Crononero Team Tri Handlebars",
    "url": "https://www.probikekit.com.au/bicycle-handlebars-stems/deda-crononero-team-tri-handlebars/10916763.html",
    "images": [
      {
        "description": "Deda Crononero Team Tri Handlebars",
        "src": "https://s1.thcdn.com/productimg/0/300/300/63/10916763-1395742995-806899.jpg"
      }
    ],
    "prices": {
      "RRP": "A$89.49",
      "rrp": "A$56.49",
      "Save:": "A$33.00"
    }
  },
  {
    "data-product-title": "Deda Parabolica/Fastblack 2 Clamp Pair - Black",
    "data-product-id": "11855675",
    "data-product-category": "",
    "data-product-is-master-product-id": "true",
    "data-product-master-product-id": "11855675",
    "data-product-brand": "Deda",
    "data-product-price": "A$59.49",
    "data-product-position": "22",
    "name": "Deda Parabolica/Fastblack 2 Clamp Pair - Black",
    "url": "https://www.probikekit.com.au/bicycle-handlebars-stems/deda-parabolica-fastblack-2-clamp-pair-black/11855675.html",
    "images": [
      {
        "description": "Deda Parabolica/Fastblack 2 Clamp Pair - Black",
        "src": "https://s3.thcdn.com/productimg/300/300/11855675-1014606425081966.jpg"
      }
    ],
    "prices": {
      "RRP": "A$69.99",
      "rrp": "A$59.49",
      "Save:": "A$10.50"
    }
  },
  {
    "data-product-title": "Deda Crononero Tri Handlebars",
    "data-product-id": "10916760",
    "data-product-category": "",
    "data-product-is-master-product-id": "true",
    "data-product-master-product-id": "10916760",
    "data-product-brand": "Deda",
    "data-product-price": "A$52.99",
    "data-product-position": "23",
    "name": "Deda Crononero Tri Handlebars",
    "url": "https://www.probikekit.com.au/bicycle-handlebars-stems/deda-crononero-tri-handlebars/10916760.html",
    "images": [
      {
        "description": "Deda Crononero Tri Handlebars",
        "src": "https://s3.thcdn.com/productimg/0/300/300/60/10916760-1394556545-481815.jpg"
      }
    ],
    "prices": {
      "RRP": "A$89.49",
      "rrp": "A$52.99",
      "Save:": "A$36.50"
    }
  },
  {
    "data-product-title": "Deda Fastblack2 TT Extensions - Black",
    "data-product-id": "11448965",
    "data-product-category": "",
    "data-product-is-master-product-id": "true",
    "data-product-master-product-id": "11448965",
    "data-product-brand": "Deda",
    "data-product-price": "A$182.49",
    "data-product-position": "24",
    "name": "Deda Fastblack2 TT Extensions - Black",
    "url": "https://www.probikekit.com.au/bicycle-handlebars-stems/deda-fastblack2-tt-extensions-black/11448965.html",
    "images": [
      {
        "description": "Deda Fastblack2 TT Extensions - Black",
        "src": "https://s2.thcdn.com/productimg/300/300/11448965-1534485042773436.jpg"
      }
    ],
    "prices": {
      "RRP": "A$322.99",
      "rrp": "A$182.49",
      "Save:": "A$140.50"
    }
  }
]