[
  {
    "data-product-title": "Park Tool HBH-2 Handlebar Holder",
    "data-product-id": "10772187",
    "data-product-category": "",
    "data-product-is-master-product-id": "false",
    "data-product-master-product-id": "10772187",
    "data-product-brand": "Park Tool",
    "data-product-price": "A$28.99",
    "data-product-position": "1",
    "name": "Park Tool HBH-2 Handlebar Holder",
    "url": "https://www.probikekit.com.au/bicycle-tools-and-maintenance-nc/park-tool-hbh-2-handlebar-holder/10772187.html",
    "images": [
      {
        "description": "Park Tool HBH-2 Handlebar Holder",
        "src": "https://s3.thcdn.com/productimg/0/300/300/87/10772187-1363093550-973956.jpg"
      }
    ],
    "prices": {
      "RRP": "A$38.99",
      "rrp": "A$28.99",
      "Save:": "A$10.00"
    }
  },
  {
    "data-product-title": "Park Tool PCS-9 Home Mechanic Repair Stand",
    "data-product-id": "10772207",
    "data-product-category": "",
    "data-product-is-master-product-id": "false",
    "data-product-master-product-id": "10772207",
    "data-product-brand": "Park Tool",
    "data-product-price": "A$232.99",
    "data-product-position": "2",
    "name": "Park Tool PCS-9 Home Mechanic Repair Stand",
    "url": "https://www.probikekit.com.au/bicycle-tools-and-maintenance-nc/park-tool-pcs-9-home-mechanic-repair-stand/10772207.html",
    "images": [
      {
        "description": "Park Tool PCS-9 Home Mechanic Repair Stand",
        "src": "https://s3.thcdn.com/productimg/0/300/300/07/10772207-1363093550-976389.jpg"
      }
    ],
    "prices": {
      "rrp": "A$232.99"
    }
  },
  {
    "data-product-title": "Buzz Rack Eco Work Stand",
    "data-product-id": "11978876",
    "data-product-category": "",
    "data-product-is-master-product-id": "false",
    "data-product-master-product-id": "11978876",
    "data-product-brand": "Buzz Rack",
    "data-product-price": "A$142.49",
    "data-product-position": "3",
    "name": "Buzz Rack Eco Work Stand",
    "url": "https://www.probikekit.com.au/bicycle-tools-and-maintenance/buzz-rack-eco-work-stand/11978876.html",
    "images": [
      {
        "description": "Buzz Rack Eco Work Stand",
        "src": "https://s3.thcdn.com/productimg/300/300/11978876-1214632007239723.jpg"
      }
    ],
    "prices": {
      "rrp": "A$142.49"
    }
  },
  {
    "data-product-title": "Buzz Rack Wall Work Stand",
    "data-product-id": "11978875",
    "data-product-category": "",
    "data-product-is-master-product-id": "false",
    "data-product-master-product-id": "11978875",
    "data-product-brand": "Buzz Rack",
    "data-product-price": "A$67.99",
    "data-product-position": "4",
    "name": "Buzz Rack Wall Work Stand",
    "url": "https://www.probikekit.com.au/bicycle-tools-and-maintenance/buzz-rack-wall-work-stand/11978875.html",
    "images": [
      {
        "description": "Buzz Rack Wall Work Stand",
        "src": "https://s4.thcdn.com/productimg/300/300/11978875-1044632008987532.jpg"
      }
    ],
    "prices": {
      "RRP": "A$97.49",
      "rrp": "A$67.99",
      "Save:": "A$29.50"
    }
  }
]